<?xml version="1.0" encoding="utf-8" ?>
<dwsync>
<file name="gl1.jpg" server="transportarlogistics.com" local="133274471039194664" remote="133241290200000000" Dst="2" />
<file name="gl3.jpg" server="transportarlogistics.com" local="133274471069558209" remote="133241290200000000" Dst="2" />
<file name="gl4.jpg" server="transportarlogistics.com" local="133274471058796579" remote="133241290200000000" Dst="2" />
<file name="gl2.jpg" server="transportarlogistics.com" local="133274471048348637" remote="133241290200000000" Dst="2" />
<file name="gl5.jpg" server="transportarlogistics.com" local="133274471066631884" remote="133241290200000000" Dst="2" />
<file name="gl6.jpg" server="transportarlogistics.com" local="133274471072989018" remote="133241290200000000" Dst="2" />
<file name="._gl1.jpg" server="transportarlogistics.com" local="133274471015822338" remote="133240517400000000" Dst="2" />
<file name="._gl2.jpg" server="transportarlogistics.com" local="133274471016271125" remote="133240517400000000" Dst="2" />
<file name="._gl3.jpg" server="transportarlogistics.com" local="133274471018574999" remote="133240517400000000" Dst="2" />
<file name="._gl4.jpg" server="transportarlogistics.com" local="133274471022255218" remote="133240517400000000" Dst="2" />
<file name="._gl5.jpg" server="transportarlogistics.com" local="133274471023960709" remote="133240517400000000" Dst="2" />
<file name="._gl6.jpg" server="transportarlogistics.com" local="133274471026897048" remote="133240517400000000" Dst="2" />
</dwsync>