<?xml version="1.0" encoding="utf-8" ?>
<dwsync>
<file name="alert_blue.svg" server="transportarlogistics.com" local="133274463994789264" remote="133266363000000000" Dst="2" />
<file name="calendar.png" server="transportarlogistics.com" local="133274463995863946" remote="133266363000000000" Dst="2" />
<file name="close_white.svg" server="transportarlogistics.com" local="133274464002061694" remote="133266363000000000" Dst="2" />
<file name="exclamation-octagon.png" server="transportarlogistics.com" local="133274464002009318" remote="133266363000000000" Dst="2" />
<file name="product_delete.png" server="transportarlogistics.com" local="133274464003167782" remote="133266363000000000" Dst="2" />
<file name="product_drag.png" server="transportarlogistics.com" local="133274464006226952" remote="133266363000000000" Dst="2" />
<file name="product_settings.png" server="transportarlogistics.com" local="133274464008093777" remote="133266363000000000" Dst="2" />
<file name="product_upload.svg" server="transportarlogistics.com" local="133274464008567413" remote="133266363000000000" Dst="2" />
<file name="sp_back_icon.svg" server="transportarlogistics.com" local="133274464010018099" remote="133266363000000000" Dst="2" />
<file name="stripeACH_plaid.svg" server="transportarlogistics.com" local="133274464011969884" remote="133266363000000000" Dst="2" />
<file name="trash_btn.svg" server="transportarlogistics.com" local="133274464013488492" remote="133266363000000000" Dst="2" />
</dwsync>